[{"time":0.0,"pose":{"rotation":{"radians":3.141592653589793},"translation":{"x":5.0,"y":0.8}},"velocity":0,"acceleration":3.0,"curvature":0,"holonomicRotation":0.0,"angularVelocity":0.0,"holonomicAngularVelocity":0.0},{"time":0.004080396777761148,"pose":{"rotation":{"radians":3.141592653589793},"translation":{"x":4.999975025543204,"y":0.8}},"velocity":0.012241190333283445,"acceleration":3.0,"curvature":0,"holonomicRotation":0.0,"angularVelocity":407.33577449297655,"holonomicAngularVelocity":0.0},{"time":0.011792934812261631,"pose":{"rotation":{"radians":0.0},"translation":{"x":5.0001586610536375,"y":0.8}},"velocity":0.03537880443678489,"acceleration":3.0,"curvature":0,"holonomicRotation":0.0,"angularVelocity":0.0,"holonomicAngularVelocity":0.0},{"time":0.019986161283525976,"pose":{"rotation":{"radians":0.0},"translation":{"x":5.000549221050685,"y":0.8}},"velocity":0.05995848385057793,"acceleration":3.0,"curvature":0,"holonomicRotation":0.0,"angularVelocity":0.0,"holonomicAngularVelocity":0.0},{"time":0.02822491768314291,"pose":{"rotation":{"radians":0.0},"translation":{"x":5.001145020053738,"y":0.8}},"velocity":0.08467475304942873,"acceleration":3.0000000000000004,"curvature":0,"holonomicRotation":0.0,"angularVelocity":0.0,"holonomicAngularVelocity":0.0},{"time":0.036462962905510425,"pose":{"rotation":{"radians":0.0},"translation":{"x":5.001944372582181,"y":0.8}},"velocity":0.10938888871653127,"acceleration":2.9999999999999987,"curvature":0,"holonomicRotation":0.0,"angularVelocity":0.0,"holonomicAngularVelocity":0.0},{"time":0.0446881197411223,"pose":{"rotation":{"radians":0.0},"translation":{"x":5.002945593155403,"y":0.8}},"velocity":0.1340643592233669,"acceleration":3.000000000000001,"curvature":0,"holonomicRotation":0.0,"angularVelocity":0.0,"holonomicAngularVelocity":0.0},{"time":0.05289577932995274,"pose":{"rotation":{"radians":0.0},"translation":{"x":5.004146996292793,"y":0.8}},"velocity":0.15868733798985823,"acceleration":3.000000000000001,"curvature":0,"holonomicRotation":0.0,"angularVelocity":0.0,"holonomicAngularVelocity":0.0},{"time":0.061083797236943724,"pose":{"rotation":{"radians":0.0},"translation":{"x":5.005546896513734,"y":0.8}},"velocity":0.18325139171083116,"acceleration":2.9999999999999973,"curvature":0,"holonomicRotation":0.0,"angularVelocity":0.0,"holonomicAngularVelocity":0.0},{"time":0.06925102767570265,"pose":{"rotation":{"radians":0.0},"translation":{"x":5.0071436083376195,"y":0.8}},"velocity":0.20775308302710793,"acceleration":2.9999999999999982,"curvature":0,"holonomicRotation":0.0,"angularVelocity":0.0,"holonomicAngularVelocity":0.0},{"time":0.07739679234276337,"pose":{"rotation":{"radians":0.0},"translation":{"x":5.008935446283831,"y":0.8}},"velocity":0.23219037702829007,"acceleration":3.0,"curvature":0,"holonomicRotation":0.0,"angularVelocity":0.0,"holonomicAngularVelocity":0.0},{"time":0.08552065553752969,"pose":{"rotation":{"radians":0.0},"translation":{"x":5.010920724871761,"y":0.8}},"velocity":0.25656196661258907,"acceleration":3.0000000000000036,"curvature":0,"holonomicRotation":0.0,"angularVelocity":0.0,"holonomicAngularVelocity":0.0},{"time":0.09362231761849184,"pose":{"rotation":{"radians":0.0},"translation":{"x":5.013097758620795,"y":0.8}},"velocity":0.2808669528554755,"acceleration":3.0000000000000018,"curvature":0,"holonomicRotation":0.0,"angularVelocity":0.0,"holonomicAngularVelocity":0.0},{"time":0.10170156001396637,"pose":{"rotation":{"radians":0.0},"translation":{"x":5.01546486205032,"y":0.8}},"velocity":0.3051046800418991,"acceleration":3.0,"curvature":0,"holonomicRotation":0.0,"angularVelocity":0.0,"holonomicAngularVelocity":0.0},{"time":0.10975821485828476,"pose":{"rotation":{"radians":0.0},"translation":{"x":5.018020349679724,"y":0.8}},"velocity":0.3292746445748543,"acceleration":3.0,"curvature":0,"holonomicRotation":0.0,"angularVelocity":0.0,"holonomicAngularVelocity":0.0},{"time":0.11779214728208942,"pose":{"rotation":{"radians":0.0},"translation":{"x":5.020762536028396,"y":0.8}},"velocity":0.3533764418462683,"acceleration":3.0000000000000053,"curvature":0,"holonomicRotation":0.0,"angularVelocity":0.0,"holonomicAngularVelocity":0.0},{"time":0.12580324460392686,"pose":{"rotation":{"radians":0.0},"translation":{"x":5.023689735615721,"y":0.8}},"velocity":0.37740973381178067,"acceleration":3.0000000000000036,"curvature":0,"holonomicRotation":0.0,"angularVelocity":0.0,"holonomicAngularVelocity":0.0},{"time":0.1337914094767967,"pose":{"rotation":{"radians":0.0},"translation":{"x":5.02680026296109,"y":0.8}},"velocity":0.4013742284303902,"acceleration":3.0,"curvature":0,"holonomicRotation":0.0,"angularVelocity":0.0,"holonomicAngularVelocity":0.0},{"time":0.14175655539804732,"pose":{"rotation":{"radians":0.0},"translation":{"x":5.030092432583888,"y":0.8}},"velocity":0.4252696661941421,"acceleration":3.0000000000000036,"curvature":0,"holonomicRotation":0.0,"angularVelocity":0.0,"holonomicAngularVelocity":0.0},{"time":0.14969860368329913,"pose":{"rotation":{"radians":0.0},"translation":{"x":5.033564559003502,"y":0.8}},"velocity":0.4490958110498975,"acceleration":3.0,"curvature":0,"holonomicRotation":0.0,"angularVelocity":0.0,"holonomicAngularVelocity":0.0},{"time":0.15761748137588028,"pose":{"rotation":{"radians":0.0},"translation":{"x":5.037214956739322,"y":0.8}},"velocity":0.47285244412764094,"acceleration":3.0,"curvature":0,"holonomicRotation":0.0,"angularVelocity":0.0,"holonomicAngularVelocity":0.0},{"time":0.16551311977065955,"pose":{"rotation":{"radians":0.0},"translation":{"x":5.041041940310733,"y":0.8}},"velocity":0.49653935931197873,"acceleration":2.9999999999999964,"curvature":0,"holonomicRotation":0.0,"angularVelocity":0.0,"holonomicAngularVelocity":0.0},{"time":0.17338545335122987,"pose":{"rotation":{"radians":0.0},"translation":{"x":5.045043824237125,"y":0.8}},"velocity":0.5201563600536897,"acceleration":3.0,"curvature":0,"holonomicRotation":0.0,"angularVelocity":0.0,"holonomicAngularVelocity":0.0},{"time":0.1812344190111711,"pose":{"rotation":{"radians":0.0},"translation":{"x":5.049218923037883,"y":0.8}},"velocity":0.5437032570335133,"acceleration":2.9999999999999893,"curvature":0,"holonomicRotation":0.0,"angularVelocity":0.0,"holonomicAngularVelocity":0.0},{"time":0.18905995547442836,"pose":{"rotation":{"radians":0.0},"translation":{"x":5.053565551232397,"y":0.8}},"velocity":0.5671798664232851,"acceleration":3.0000000000000036,"curvature":0,"holonomicRotation":0.0,"angularVelocity":-3.1874961186875962e-12,"holonomicAngularVelocity":0.0},{"time":0.19686200285757716,"pose":{"rotation":{"radians":-2.4868995751603507e-14},"translation":{"x":5.058082023340053,"y":0.7999999999999999}},"velocity":0.5905860085727315,"acceleration":2.9999999999999964,"curvature":0,"holonomicRotation":0.0,"angularVelocity":3.197145647955299e-12,"holonomicAngularVelocity":0.0},{"time":0.2046405023349182,"pose":{"rotation":{"radians":0.0},"translation":{"x":5.06276665388024,"y":0.7999999999999999}},"velocity":0.6139215070047546,"acceleration":2.999999999999993,"curvature":0,"holonomicRotation":0.0,"angularVelocity":0.0,"holonomicAngularVelocity":0.0},{"time":0.21239539587906411,"pose":{"rotation":{"radians":0.0},"translation":{"x":5.067617757372345,"y":0.7999999999999999}},"velocity":0.6371861876371923,"acceleration":2.9999999999999964,"curvature":0,"holonomicRotation":0.0,"angularVelocity":0.0,"holonomicAngularVelocity":0.0},{"time":0.22012662605773917,"pose":{"rotation":{"radians":0.0},"translation":{"x":5.072633648335754,"y":0.7999999999999999}},"velocity":0.6603798781732174,"acceleration":3.0,"curvature":0,"holonomicRotation":0.0,"angularVelocity":0.0,"holonomicAngularVelocity":0.0},{"time":0.22783413587293067,"pose":{"rotation":{"radians":0.0},"translation":{"x":5.077812641289856,"y":0.7999999999999999}},"velocity":0.683502407618792,"acceleration":3.0000000000000107,"curvature":0,"holonomicRotation":0.0,"angularVelocity":0.0,"holonomicAngularVelocity":0.0},{"time":0.23551786863226953,"pose":{"rotation":{"radians":0.0},"translation":{"x":5.083153050754039,"y":0.7999999999999999}},"velocity":0.7065536058968086,"acceleration":3.0,"curvature":0,"holonomicRotation":0.0,"angularVelocity":0.0,"holonomicAngularVelocity":0.0},{"time":0.24317776784522685,"pose":{"rotation":{"radians":0.0},"translation":{"x":5.088653191247689,"y":0.7999999999999999}},"velocity":0.7295333035356805,"acceleration":2.9999999999999893,"curvature":0,"holonomicRotation":0.0,"angularVelocity":0.0,"holonomicAngularVelocity":0.0},{"time":0.2508137771385865,"pose":{"rotation":{"radians":0.0},"translation":{"x":5.094311377290195,"y":0.7999999999999999}},"velocity":0.7524413314157594,"acceleration":3.0000000000000036,"curvature":0,"holonomicRotation":0.0,"angularVelocity":0.0,"holonomicAngularVelocity":0.0},{"time":0.25842584018700127,"pose":{"rotation":{"radians":0.0},"translation":{"x":5.100125923400944,"y":0.7999999999999999}},"velocity":0.7752775205610039,"acceleration":3.0000000000000147,"curvature":0,"holonomicRotation":0.0,"angularVelocity":-2.458038769087743e-12,"holonomicAngularVelocity":0.0},{"time":0.2660139006554799,"pose":{"rotation":{"radians":-1.865174681370263e-14},"translation":{"x":5.106095144099323,"y":0.7999999999999998}},"velocity":0.7980417019664398,"acceleration":2.999999999999993,"curvature":0,"holonomicRotation":0.0,"angularVelocity":2.4658571027315092e-12,"holonomicAngularVelocity":0.0},{"time":0.27357790215136607,"pose":{"rotation":{"radians":0.0},"translation":{"x":5.112217353904722,"y":0.7999999999999998}},"velocity":0.8207337064540983,"acceleration":3.0000000000000075,"curvature":0,"holonomicRotation":0.0,"angularVelocity":0.0,"holonomicAngularVelocity":0.0},{"time":0.2811177881839065,"pose":{"rotation":{"radians":0.0},"translation":{"x":5.118490867336526,"y":0.7999999999999998}},"velocity":0.8433533645517195,"acceleration":3.0,"curvature":0,"holonomicRotation":0.0,"angularVelocity":0.0,"holonomicAngularVelocity":0.0},{"time":0.2886335021299667,"pose":{"rotation":{"radians":0.0},"translation":{"x":5.124913998914122,"y":0.7999999999999998}},"velocity":0.8659005063899001,"acceleration":3.0,"curvature":0,"holonomicRotation":0.0,"angularVelocity":0.0,"holonomicAngularVelocity":0.0},{"time":0.2961249872047191,"pose":{"rotation":{"radians":0.0},"translation":{"x":5.131485063156901,"y":0.7999999999999998}},"velocity":0.8883749616141573,"acceleration":3.0,"curvature":0,"holonomicRotation":0.0,"angularVelocity":0.0,"holonomicAngularVelocity":0.0},{"time":0.3035921864363868,"pose":{"rotation":{"radians":0.0},"translation":{"x":5.138202374584247,"y":0.7999999999999998}},"velocity":0.9107765593091606,"acceleration":3.0000000000000147,"curvature":0,"holonomicRotation":0.0,"angularVelocity":0.0,"holonomicAngularVelocity":0.0},{"time":0.3110350426443316,"pose":{"rotation":{"radians":0.0},"translation":{"x":5.14506424771555,"y":0.7999999999999998}},"velocity":0.933105127932995,"acceleration":3.0,"curvature":0,"holonomicRotation":0.0,"angularVelocity":0.0,"holonomicAngularVelocity":0.0},{"time":0.318453498419877,"pose":{"rotation":{"radians":0.0},"translation":{"x":5.152068997070196,"y":0.7999999999999998}},"velocity":0.9553604952596312,"acceleration":2.9999999999999925,"curvature":0,"holonomicRotation":0.0,"angularVelocity":0.0,"holonomicAngularVelocity":0.0},{"time":0.3258474961094174,"pose":{"rotation":{"radians":0.0},"translation":{"x":5.159214937167573,"y":0.7999999999999998}},"velocity":0.9775424883282523,"acceleration":3.0000000000000075,"curvature":0,"holonomicRotation":0.0,"angularVelocity":0.0,"holonomicAngularVelocity":0.0},{"time":0.3332169777994128,"pose":{"rotation":{"radians":0.0},"translation":{"x":5.16650038252707,"y":0.7999999999999998}},"velocity":0.9996509333982385,"acceleration":3.0,"curvature":0,"holonomicRotation":0.0,"angularVelocity":0.0,"holonomicAngularVelocity":0.0},{"time":0.3405618853029635,"pose":{"rotation":{"radians":0.0},"translation":{"x":5.1739236476680714,"y":0.7999999999999998}},"velocity":1.0216856559088907,"acceleration":3.0000000000000075,"curvature":0,"holonomicRotation":0.0,"angularVelocity":0.0,"holonomicAngularVelocity":0.0},{"time":0.34788216014771467,"pose":{"rotation":{"radians":0.0},"translation":{"x":5.181483047109968,"y":0.7999999999999998}},"velocity":1.0436464804431442,"acceleration":3.0,"curvature":0,"holonomicRotation":0.0,"angularVelocity":0.0,"holonomicAngularVelocity":0.0},{"time":0.3551777435648597,"pose":{"rotation":{"radians":0.0},"translation":{"x":5.189176895372146,"y":0.7999999999999998}},"velocity":1.0655332306945793,"acceleration":2.9999999999999925,"curvature":0,"holonomicRotation":0.0,"angularVelocity":0.0,"holonomicAngularVelocity":0.0},{"time":0.3624485764790954,"pose":{"rotation":{"radians":0.0},"translation":{"x":5.197003506973992,"y":0.7999999999999998}},"velocity":1.0873457294372864,"acceleration":3.0,"curvature":0,"holonomicRotation":0.0,"angularVelocity":0.0,"holonomicAngularVelocity":0.0},{"time":0.3696945994993603,"pose":{"rotation":{"radians":0.0},"translation":{"x":5.204961196434897,"y":0.7999999999999998}},"velocity":1.109083798498081,"acceleration":3.0,"curvature":0,"holonomicRotation":0.0,"angularVelocity":0.0,"holonomicAngularVelocity":0.0},{"time":0.3769157529102369,"pose":{"rotation":{"radians":0.0},"translation":{"x":5.213048278274244,"y":0.7999999999999998}},"velocity":1.1307472587307108,"acceleration":3.0,"curvature":0,"holonomicRotation":0.0,"angularVelocity":0.0,"holonomicAngularVelocity":0.0},{"time":0.3841119766639378,"pose":{"rotation":{"radians":0.0},"translation":{"x":5.221263067011424,"y":0.7999999999999998}},"velocity":1.1523359299918137,"acceleration":3.0000000000000075,"curvature":0,"holonomicRotation":0.0,"angularVelocity":0.0,"holonomicAngularVelocity":0.0},{"time":0.39128321037275504,"pose":{"rotation":{"radians":0.0},"translation":{"x":5.229603877165823,"y":0.7999999999999998}},"velocity":1.1738496311182653,"acceleration":3.0,"curvature":0,"holonomicRotation":0.0,"angularVelocity":0.0,"holonomicAngularVelocity":0.0},{"time":0.3984293933019331,"pose":{"rotation":{"radians":0.0},"translation":{"x":5.238069023256828,"y":0.7999999999999998}},"velocity":1.1952881799057995,"acceleration":2.9999999999999925,"curvature":0,"holonomicRotation":0.0,"angularVelocity":-1.7461555669617354e-12,"holonomicAngularVelocity":0.0},{"time":0.40555046436287956,"pose":{"rotation":{"radians":-1.2434497875801753e-14},"translation":{"x":5.246656819803829,"y":0.7999999999999997}},"velocity":1.216651393088639,"acceleration":3.000000000000008,"curvature":0,"holonomicRotation":0.0,"angularVelocity":1.752350206382926e-12,"holonomicAngularVelocity":0.0},{"time":0.4126463621066691,"pose":{"rotation":{"radians":0.0},"translation":{"x":5.255365581326211,"y":0.7999999999999997}},"velocity":1.2379390863200075,"acceleration":2.999999999999992,"curvature":0,"holonomicRotation":0.0,"angularVelocity":0.0,"holonomicAngularVelocity":0.0},{"time":0.4197170247178085,"pose":{"rotation":{"radians":0.0},"translation":{"x":5.264193622343362,"y":0.7999999999999997}},"velocity":1.2591510741534255,"acceleration":2.999999999999992,"curvature":0,"holonomicRotation":0.0,"angularVelocity":0.0,"holonomicAngularVelocity":0.0},{"time":0.42676239000819743,"pose":{"rotation":{"radians":0.0},"translation":{"x":5.273139257374671,"y":0.7999999999999997}},"velocity":1.2802871700245926,"acceleration":3.0000000000000235,"curvature":0,"holonomicRotation":0.0,"angularVelocity":0.0,"holonomicAngularVelocity":0.0},{"time":0.4337823954112759,"pose":{"rotation":{"radians":0.0},"translation":{"x":5.282200800939525,"y":0.7999999999999997}},"velocity":1.301347186233828,"acceleration":3.0,"curvature":0,"holonomicRotation":0.0,"angularVelocity":0.0,"holonomicAngularVelocity":0.0},{"time":0.44077697797631765,"pose":{"rotation":{"radians":0.0},"translation":{"x":5.291376567557311,"y":0.7999999999999997}},"velocity":1.3223309339289533,"acceleration":3.000000000000008,"curvature":0,"holonomicRotation":0.0,"angularVelocity":0.0,"holonomicAngularVelocity":0.0},{"time":0.4477460743628458,"pose":{"rotation":{"radians":0.0},"translation":{"x":5.300664871747417,"y":0.7999999999999997}},"velocity":1.3432382230885378,"acceleration":3.000000000000008,"curvature":0,"holonomicRotation":0.0,"angularVelocity":0.0,"holonomicAngularVelocity":0.0},{"time":0.4546896208351524,"pose":{"rotation":{"radians":0.0},"translation":{"x":5.31006402802923,"y":0.7999999999999997}},"velocity":1.3640688625054576,"acceleration":2.999999999999992,"curvature":0,"holonomicRotation":0.0,"angularVelocity":0.0,"holonomicAngularVelocity":0.0},{"time":0.461607553256897,"pose":{"rotation":{"radians":0.0},"translation":{"x":5.319572350922137,"y":0.7999999999999997}},"velocity":1.3848226597706912,"acceleration":2.999999999999976,"curvature":0,"holonomicRotation":0.0,"angularVelocity":0.0,"holonomicAngularVelocity":0.0},{"time":0.46849980708578004,"pose":{"rotation":{"radians":0.0},"translation":{"x":5.329188154945528,"y":0.7999999999999997}},"velocity":1.4054994212573402,"acceleration":2.999999999999984,"curvature":0,"holonomicRotation":0.0,"angularVelocity":-1.5521918118448157e-12,"holonomicAngularVelocity":0.0},{"time":0.4753663173682522,"pose":{"rotation":{"radians":-1.0658141036401503e-14},"translation":{"x":5.338909754618789,"y":0.7999999999999996}},"velocity":1.4260989521047567,"acceleration":3.000000000000008,"curvature":0,"holonomicRotation":0.0,"angularVelocity":1.5580479933441407e-12,"holonomicAngularVelocity":0.0},{"time":0.482207018734277,"pose":{"rotation":{"radians":0.0},"translation":{"x":5.348735464461307,"y":0.7999999999999996}},"velocity":1.4466210562028312,"acceleration":3.000000000000008,"curvature":0,"holonomicRotation":0.0,"angularVelocity":0.0,"holonomicAngularVelocity":0.0},{"time":0.48902184539211374,"pose":{"rotation":{"radians":0.0},"translation":{"x":5.358663598992471,"y":0.7999999999999996}},"velocity":1.4670655361763414,"acceleration":3.0,"curvature":0,"holonomicRotation":0.0,"angularVelocity":0.0,"holonomicAngularVelocity":0.0},{"time":0.4958107311231167,"pose":{"rotation":{"radians":0.0},"translation":{"x":5.368692472731667,"y":0.7999999999999996}},"velocity":1.4874321933693502,"acceleration":2.999999999999992,"curvature":0,"holonomicRotation":0.0,"angularVelocity":0.0,"holonomicAngularVelocity":0.0},{"time":0.5025736092765426,"pose":{"rotation":{"radians":0.0},"translation":{"x":5.3788204001982844,"y":0.7999999999999996}},"velocity":1.507720827829628,"acceleration":3.0,"curvature":0,"holonomicRotation":0.0,"angularVelocity":0.0,"holonomicAngularVelocity":0.0},{"time":0.5093104127643585,"pose":{"rotation":{"radians":0.0},"translation":{"x":5.38904569591171,"y":0.7999999999999996}},"velocity":1.5279312382930756,"acceleration":3.0,"curvature":0,"holonomicRotation":0.0,"angularVelocity":0.0,"holonomicAngularVelocity":0.0},{"time":0.5160210740560389,"pose":{"rotation":{"radians":0.0},"translation":{"x":5.39936667439133,"y":0.7999999999999996}},"velocity":1.5480632221681168,"acceleration":2.9999999999999836,"curvature":0,"holonomicRotation":0.0,"angularVelocity":0.0,"holonomicAngularVelocity":0.0},{"time":0.5227055251733521,"pose":{"rotation":{"radians":0.0},"translation":{"x":5.409781650156533,"y":0.7999999999999996}},"velocity":1.5681165755200566,"acceleration":3.0000000000000333,"curvature":0,"holonomicRotation":0.0,"angularVelocity":0.0,"holonomicAngularVelocity":0.0},{"time":0.5293636976851234,"pose":{"rotation":{"radians":0.0},"translation":{"x":5.420288937726708,"y":0.7999999999999996}},"velocity":1.5880910930553704,"acceleration":3.000000000000017,"curvature":0,"holonomicRotation":0.0,"angularVelocity":0.0,"holonomicAngularVelocity":0.0},{"time":0.535995522701967,"pose":{"rotation":{"radians":0.0},"translation":{"x":5.43088685162124,"y":0.7999999999999996}},"velocity":1.6079865681059016,"acceleration":3.000000000000017,"curvature":0,"holonomicRotation":0.0,"angularVelocity":-1.6135476814849195e-12,"holonomicAngularVelocity":0.0},{"time":0.542600930870998,"pose":{"rotation":{"radians":-1.0658141036401503e-14},"translation":{"x":5.441573706359518,"y":0.7999999999999995}},"velocity":1.6278027926129948,"acceleration":3.0000000000000338,"curvature":0,"holonomicRotation":0.0,"angularVelocity":1.6200438076684825e-12,"holonomicAngularVelocity":0.0},{"time":0.5491798523704977,"pose":{"rotation":{"radians":0.0},"translation":{"x":5.4523478164609305,"y":0.7999999999999995}},"velocity":1.6475395571114937,"acceleration":2.999999999999983,"curvature":0,"holonomicRotation":0.0,"angularVelocity":0.0,"holonomicAngularVelocity":0.0},{"time":0.5557322169045411,"pose":{"rotation":{"radians":0.0},"translation":{"x":5.463207496444862,"y":0.7999999999999995}},"velocity":1.6671966507136238,"acceleration":2.999999999999983,"curvature":0,"holonomicRotation":0.0,"angularVelocity":0.0,"holonomicAngularVelocity":0.0},{"time":0.5622579536975866,"pose":{"rotation":{"radians":0.0},"translation":{"x":5.474151060830704,"y":0.7999999999999995}},"velocity":1.68677386109276,"acceleration":2.999999999999983,"curvature":0,"holonomicRotation":0.0,"angularVelocity":0.0,"holonomicAngularVelocity":0.0},{"time":0.568756991489003,"pose":{"rotation":{"radians":0.0},"translation":{"x":5.485176824137841,"y":0.7999999999999995}},"velocity":1.7062709744670093,"acceleration":2.999999999999966,"curvature":0,"holonomicRotation":0.0,"angularVelocity":0.0,"holonomicAngularVelocity":0.0},{"time":0.5752292585275629,"pose":{"rotation":{"radians":0.0},"translation":{"x":5.4962831008856625,"y":0.7999999999999995}},"velocity":1.7256877755826887,"acceleration":2.9999999999999827,"curvature":0,"holonomicRotation":0.0,"angularVelocity":-1.5157982715561006e-12,"holonomicAngularVelocity":0.0},{"time":0.581674682565863,"pose":{"rotation":{"radians":-9.769962616701378e-15},"translation":{"x":5.507468205593554,"y":0.7999999999999994}},"velocity":1.745024047697589,"acceleration":3.0,"curvature":0,"holonomicRotation":0.0,"angularVelocity":1.5221547090139937e-12,"holonomicAngularVelocity":0.0},{"time":0.5880931908547018,"pose":{"rotation":{"radians":0.0},"translation":{"x":5.518730452780905,"y":0.7999999999999994}},"velocity":1.7642795725641054,"acceleration":3.0,"curvature":0,"holonomicRotation":0.0,"angularVelocity":0.0,"holonomicAngularVelocity":0.0},{"time":0.5944847101373842,"pose":{"rotation":{"radians":0.0},"translation":{"x":5.530068156967102,"y":0.7999999999999994}},"velocity":1.7834541304121527,"acceleration":3.0,"curvature":0,"holonomicRotation":0.0,"angularVelocity":0.0,"holonomicAngularVelocity":0.0},{"time":0.6008491666439673,"pose":{"rotation":{"radians":0.0},"translation":{"x":5.541479632671533,"y":0.7999999999999994}},"velocity":1.802547499931902,"acceleration":3.000000000000035,"curvature":0,"holonomicRotation":0.0,"angularVelocity":0.0,"holonomicAngularVelocity":0.0},{"time":0.6071864860854413,"pose":{"rotation":{"radians":0.0},"translation":{"x":5.552963194413587,"y":0.7999999999999994}},"velocity":1.8215594582563241,"acceleration":2.9999999999999827,"curvature":0,"holonomicRotation":0.0,"angularVelocity":0.0,"holonomicAngularVelocity":0.0},{"time":0.613496593647832,"pose":{"rotation":{"radians":0.0},"translation":{"x":5.564517156712648,"y":0.7999999999999994}},"velocity":1.8404897809434964,"acceleration":3.0000000000000178,"curvature":0,"holonomicRotation":0.0,"angularVelocity":0.0,"holonomicAngularVelocity":0.0},{"time":0.6197794139862438,"pose":{"rotation":{"radians":0.0},"translation":{"x":5.576139834088106,"y":0.7999999999999994}},"velocity":1.8593382419587317,"acceleration":3.0,"curvature":0,"holonomicRotation":0.0,"angularVelocity":0.0,"holonomicAngularVelocity":0.0},{"time":0.6260348712188167,"pose":{"rotation":{"radians":0.0},"translation":{"x":5.587829541059349,"y":0.7999999999999994}},"velocity":1.8781046136564503,"acceleration":2.9999999999999822,"curvature":0,"holonomicRotation":0.0,"angularVelocity":0.0,"holonomicAngularVelocity":0.0},{"time":0.6322628889206108,"pose":{"rotation":{"radians":0.0},"translation":{"x":5.599584592145763,"y":0.7999999999999994}},"velocity":1.8967886667618323,"acceleration":2.9999999999999822,"curvature":0,"holonomicRotation":0.0,"angularVelocity":0.0,"holonomicAngularVelocity":0.0},{"time":0.6384633901174122,"pose":{"rotation":{"radians":0.0},"translation":{"x":5.611403301866736,"y":0.7999999999999994}},"velocity":1.9153901703522365,"acceleration":3.0,"curvature":0,"holonomicRotation":0.0,"angularVelocity":0.0,"holonomicAngularVelocity":0.0},{"time":0.644636297279455,"pose":{"rotation":{"radians":0.0},"translation":{"x":5.623283984741657,"y":0.7999999999999994}},"velocity":1.9339088918383651,"acceleration":3.0,"curvature":0,"holonomicRotation":0.0,"angularVelocity":0.0,"holonomicAngularVelocity":0.0},{"time":0.6507815323150589,"pose":{"rotation":{"radians":0.0},"translation":{"x":5.635224955289912,"y":0.7999999999999994}},"velocity":1.9523445969451767,"acceleration":3.000000000000018,"curvature":0,"holonomicRotation":0.0,"angularVelocity":0.0,"holonomicAngularVelocity":0.0},{"time":0.6568990165641803,"pose":{"rotation":{"radians":0.0},"translation":{"x":5.647224528030889,"y":0.7999999999999994}},"velocity":1.970697049692541,"acceleration":3.0,"curvature":0,"holonomicRotation":0.0,"angularVelocity":-1.458503859974095e-12,"holonomicAngularVelocity":0.0},{"time":0.6629886707918756,"pose":{"rotation":{"radians":-8.881784197001252e-15},"translation":{"x":5.659281017483975,"y":0.7999999999999993}},"velocity":1.9889660123756272,"acceleration":3.0000000000000364,"curvature":0,"holonomicRotation":0.0,"angularVelocity":1.4652191887127694e-12,"holonomicAngularVelocity":0.0},{"time":0.6690504151816717,"pose":{"rotation":{"radians":0.0},"translation":{"x":5.671392738168559,"y":0.7999999999999993}},"velocity":2.007151245545016,"acceleration":3.0000000000000364,"curvature":0,"holonomicRotation":0.0,"angularVelocity":0.0,"holonomicAngularVelocity":0.0},{"time":0.675084169328842,"pose":{"rotation":{"radians":0.0},"translation":{"x":5.683558004604027,"y":0.7999999999999993}},"velocity":2.0252525079865267,"acceleration":3.000000000000037,"curvature":0,"holonomicRotation":0.0,"angularVelocity":0.0,"holonomicAngularVelocity":0.0},{"time":0.6810898522335901,"pose":{"rotation":{"radians":0.0},"translation":{"x":5.695775131309769,"y":0.7999999999999993}},"velocity":2.0432695567007713,"acceleration":3.000000000000037,"curvature":0,"holonomicRotation":0.0,"angularVelocity":0.0,"holonomicAngularVelocity":0.0},{"time":0.6870673822941294,"pose":{"rotation":{"radians":0.0},"translation":{"x":5.708042432805169,"y":0.7999999999999993}},"velocity":2.061202146882389,"acceleration":2.9999999999999627,"curvature":0,"holonomicRotation":0.0,"angularVelocity":0.0,"holonomicAngularVelocity":0.0},{"time":0.6930166772996683,"pose":{"rotation":{"radians":0.0},"translation":{"x":5.720358223609617,"y":0.7999999999999993}},"velocity":2.0790500318990057,"acceleration":3.0,"curvature":0,"holonomicRotation":0.0,"angularVelocity":0.0,"holonomicAngularVelocity":0.0},{"time":0.6989376544232883,"pose":{"rotation":{"radians":0.0},"translation":{"x":5.7327208182425,"y":0.7999999999999993}},"velocity":2.0968129632698655,"acceleration":3.0,"curvature":0,"holonomicRotation":0.0,"angularVelocity":0.0,"holonomicAngularVelocity":0.0},{"time":0.7048302302147177,"pose":{"rotation":{"radians":0.0},"translation":{"x":5.745128531223206,"y":0.7999999999999993}},"velocity":2.114490690644154,"acceleration":3.0,"curvature":0,"holonomicRotation":0.0,"angularVelocity":0.0,"holonomicAngularVelocity":0.0},{"time":0.7106943205929975,"pose":{"rotation":{"radians":0.0},"translation":{"x":5.757579677071122,"y":0.7999999999999993}},"velocity":2.1320829617789934,"acceleration":3.0,"curvature":0,"holonomicRotation":0.0,"angularVelocity":-1.522020971999284e-12,"holonomicAngularVelocity":0.0},{"time":0.7165298408390388,"pose":{"rotation":{"radians":-8.881784197001252e-15},"translation":{"x":5.7700725703056355,"y":0.7999999999999992}},"velocity":2.1495895225171173,"acceleration":3.000000000000019,"curvature":0,"holonomicRotation":0.0,"angularVelocity":1.5295317836518403e-12,"holonomicAngularVelocity":0.0},{"time":0.7223367055880638,"pose":{"rotation":{"radians":0.0},"translation":{"x":5.782605525446134,"y":0.7999999999999992}},"velocity":2.1670101167641924,"acceleration":3.0,"curvature":0,"holonomicRotation":0.0,"angularVelocity":0.0,"holonomicAngularVelocity":0.0},{"time":0.7281148288219369,"pose":{"rotation":{"radians":0.0},"translation":{"x":5.795176857012006,"y":0.7999999999999992}},"velocity":2.1843444864658115,"acceleration":2.999999999999981,"curvature":0,"holonomicRotation":0.0,"angularVelocity":0.0,"holonomicAngularVelocity":0.0},{"time":0.7338641238613728,"pose":{"rotation":{"radians":0.0},"translation":{"x":5.8077848795226386,"y":0.7999999999999992}},"velocity":2.201592371584119,"acceleration":2.9999999999999423,"curvature":0,"holonomicRotation":0.0,"angularVelocity":0.0,"holonomicAngularVelocity":0.0},{"time":0.7395845033580274,"pose":{"rotation":{"radians":0.0},"translation":{"x":5.820427907497418,"y":0.7999999999999992}},"velocity":2.2187535100740825,"acceleration":2.9999999999999805,"curvature":0,"holonomicRotation":0.0,"angularVelocity":0.0,"holonomicAngularVelocity":0.0},{"time":0.7452758792864677,"pose":{"rotation":{"radians":0.0},"translation":{"x":5.833104255455734,"y":0.7999999999999992}},"velocity":2.2358276378594035,"acceleration":3.000000000000039,"curvature":0,"holonomicRotation":0.0,"angularVelocity":0.0,"holonomicAngularVelocity":0.0},{"time":0.7509381629360101,"pose":{"rotation":{"radians":0.0},"translation":{"x":5.845812237916973,"y":0.7999999999999992}},"velocity":2.2528144888080313,"acceleration":3.0000000000000586,"curvature":0,"holonomicRotation":0.0,"angularVelocity":0.0,"holonomicAngularVelocity":0.0},{"time":0.7565712649024386,"pose":{"rotation":{"radians":0.0},"translation":{"x":5.858550169400522,"y":0.7999999999999992}},"velocity":2.2697137947073167,"acceleration":2.9999999999999805,"curvature":0,"holonomicRotation":0.0,"angularVelocity":0.0,"holonomicAngularVelocity":0.0},{"time":0.7621750950795854,"pose":{"rotation":{"radians":0.0},"translation":{"x":5.871316364425771,"y":0.7999999999999992}},"velocity":2.2865252852387568,"acceleration":2.99999999999998,"curvature":0,"holonomicRotation":0.0,"angularVelocity":-1.5932973119974976e-12,"holonomicAngularVelocity":0.0},{"time":0.7677495626507798,"pose":{"rotation":{"radians":-8.881784197001252e-15},"translation":{"x":5.8841091375121035,"y":0.799999999999999}},"velocity":2.30324868795234,"acceleration":3.0,"curvature":0,"holonomicRotation":0.0,"angularVelocity":1.6017606287360065e-12,"holonomicAngularVelocity":0.0},{"time":0.7732945760801647,"pose":{"rotation":{"radians":0.0},"translation":{"x":5.896926803178911,"y":0.799999999999999}},"velocity":2.319883728240495,"acceleration":3.00000000000002,"curvature":0,"holonomicRotation":0.0,"angularVelocity":0.0,"holonomicAngularVelocity":0.0},{"time":0.778810043103867,"pose":{"rotation":{"radians":0.0},"translation":{"x":5.909767675945579,"y":0.799999999999999}},"velocity":2.336430129311602,"acceleration":3.0,"curvature":0,"holonomicRotation":0.0,"angularVelocity":0.0,"holonomicAngularVelocity":0.0},{"time":0.7842958707210296,"pose":{"rotation":{"radians":0.0},"translation":{"x":5.922630070331495,"y":0.799999999999999}},"velocity":2.3528876121630895,"acceleration":3.0,"curvature":0,"holonomicRotation":0.0,"angularVelocity":0.0,"holonomicAngularVelocity":0.0},{"time":0.7897519651846984,"pose":{"rotation":{"radians":0.0},"translation":{"x":5.935512300856048,"y":0.799999999999999}},"velocity":2.3692558955540957,"acceleration":2.999999999999959,"curvature":0,"holonomicRotation":0.0,"angularVelocity":0.0,"holonomicAngularVelocity":0.0},{"time":0.7951782319925581,"pose":{"rotation":{"radians":0.0},"translation":{"x":5.948412682038624,"y":0.799999999999999}},"velocity":2.385534695977675,"acceleration":3.0,"curvature":0,"holonomicRotation":0.0,"angularVelocity":0.0,"holonomicAngularVelocity":0.0},{"time":0.8005745758775189,"pose":{"rotation":{"radians":0.0},"translation":{"x":5.961329528398612,"y":0.799999999999999}},"velocity":2.4017237276325574,"acceleration":3.0000000000000204,"curvature":0,"holonomicRotation":0.0,"angularVelocity":0.0,"holonomicAngularVelocity":0.0},{"time":0.8059409007981457,"pose":{"rotation":{"radians":0.0},"translation":{"x":5.974261154455398,"y":0.799999999999999}},"velocity":2.417822702394438,"acceleration":3.0,"curvature":0,"holonomicRotation":0.0,"angularVelocity":0.0,"holonomicAngularVelocity":0.0},{"time":0.8112771099289325,"pose":{"rotation":{"radians":0.0},"translation":{"x":5.98720587472837,"y":0.799999999999999}},"velocity":2.4338313297867984,"acceleration":3.000000000000021,"curvature":0,"holonomicRotation":0.0,"angularVelocity":0.0,"holonomicAngularVelocity":0.0},{"time":0.8165831056504124,"pose":{"rotation":{"radians":0.0},"translation":{"x":6.000162003736917,"y":0.799999999999999}},"velocity":2.449749316951238,"acceleration":3.0,"curvature":0,"holonomicRotation":0.0,"angularVelocity":0.0,"holonomicAngularVelocity":0.0},{"time":0.821858789539102,"pose":{"rotation":{"radians":0.0},"translation":{"x":6.013127856000425,"y":0.799999999999999}},"velocity":2.465576368617307,"acceleration":3.000000000000042,"curvature":0,"holonomicRotation":0.0,"angularVelocity":0.0,"holonomicAngularVelocity":0.0},{"time":0.8271040623572805,"pose":{"rotation":{"radians":0.0},"translation":{"x":6.026101746038282,"y":0.799999999999999}},"velocity":2.4813121870718424,"acceleration":2.9999999999999787,"curvature":0,"holonomicRotation":0.0,"angularVelocity":0.0,"holonomicAngularVelocity":0.0},{"time":0.8323188240425936,"pose":{"rotation":{"radians":0.0},"translation":{"x":6.039081988369877,"y":0.799999999999999}},"velocity":2.4969564721277817,"acceleration":3.0,"curvature":0,"holonomicRotation":0.0,"angularVelocity":0.0,"holonomicAngularVelocity":0.0},{"time":0.8375029736974813,"pose":{"rotation":{"radians":0.0},"translation":{"x":6.052066897514594,"y":0.799999999999999}},"velocity":2.512508921092445,"acceleration":3.0000000000000426,"curvature":0,"holonomicRotation":0.0,"angularVelocity":0.0,"holonomicAngularVelocity":0.0},{"time":0.8426564095784301,"pose":{"rotation":{"radians":0.0},"translation":{"x":6.065054787991825,"y":0.799999999999999}},"velocity":2.5279692287352913,"acceleration":2.999999999999957,"curvature":0,"holonomicRotation":0.0,"angularVelocity":-1.7314069241540101e-12,"holonomicAngularVelocity":0.0},{"time":0.8477862170622145,"pose":{"rotation":{"radians":-8.881784197001252e-15},"translation":{"x":6.078043974320953,"y":0.7999999999999989}},"velocity":2.5362310829481634,"acceleration":1.6105583375181904,"curvature":0,"holonomicRotation":0.0,"angularVelocity":1.7290146536753745e-12,"holonomicAngularVelocity":0.0},{"time":0.8529231221648527,"pose":{"rotation":{"radians":0.0},"translation":{"x":6.091032771021369,"y":0.7999999999999989}},"velocity":2.5208203676402485,"acceleration":-3.000000000000043,"curvature":0,"holonomicRotation":0.0,"angularVelocity":0.0,"holonomicAngularVelocity":0.0},{"time":0.8580907965641721,"pose":{"rotation":{"radians":0.0},"translation":{"x":6.10401949261246,"y":0.7999999999999989}},"velocity":2.50531734444229,"acceleration":-3.000000000000043,"curvature":0,"holonomicRotation":0.0,"angularVelocity":0.0,"holonomicAngularVelocity":0.0},{"time":0.863289138068347,"pose":{"rotation":{"radians":0.0},"translation":{"x":6.117002453613613,"y":0.7999999999999989}},"velocity":2.4897223199297653,"acceleration":-3.0000000000000213,"curvature":0,"holonomicRotation":0.0,"angularVelocity":0.0,"holonomicAngularVelocity":0.0},{"time":0.8685180453377394,"pose":{"rotation":{"radians":0.0},"translation":{"x":6.129979968544214,"y":0.7999999999999989}},"velocity":2.474035598121588,"acceleration":-3.0000000000000213,"curvature":0,"holonomicRotation":0.0,"angularVelocity":0.0,"holonomicAngularVelocity":0.0},{"time":0.8737774178740656,"pose":{"rotation":{"radians":0.0},"translation":{"x":6.142950351923655,"y":0.7999999999999989}},"velocity":2.4582574805126094,"acceleration":-2.9999999999999787,"curvature":0,"holonomicRotation":0.0,"angularVelocity":0.0,"holonomicAngularVelocity":0.0},{"time":0.8790671560097422,"pose":{"rotation":{"radians":0.0},"translation":{"x":6.155911918271318,"y":0.7999999999999989}},"velocity":2.4423882661055796,"acceleration":-3.000000000000021,"curvature":0,"holonomicRotation":0.0,"angularVelocity":0.0,"holonomicAngularVelocity":0.0},{"time":0.8843871608974181,"pose":{"rotation":{"radians":0.0},"translation":{"x":6.168862982106595,"y":0.7999999999999989}},"velocity":2.4264282514425517,"acceleration":-3.000000000000021,"curvature":0,"holonomicRotation":0.0,"angularVelocity":0.0,"holonomicAngularVelocity":0.0},{"time":0.8897373344996747,"pose":{"rotation":{"radians":0.0},"translation":{"x":6.181801857948871,"y":0.7999999999999989}},"velocity":2.410377730635782,"acceleration":-2.999999999999938,"curvature":0,"holonomicRotation":0.0,"angularVelocity":-1.6508140551612397e-12,"holonomicAngularVelocity":0.0},{"time":0.8951175795789025,"pose":{"rotation":{"radians":-8.881784197001252e-15},"translation":{"x":6.194726860317536,"y":0.7999999999999988}},"velocity":2.394236995398099,"acceleration":-3.0,"curvature":0,"holonomicRotation":0.0,"angularVelocity":1.6416678099929692e-12,"holonomicAngularVelocity":0.0},{"time":0.9005277996873416,"pose":{"rotation":{"radians":0.0},"translation":{"x":6.207636303731975,"y":0.7999999999999988}},"velocity":2.3780063350727816,"acceleration":-2.999999999999959,"curvature":0,"holonomicRotation":0.0,"angularVelocity":0.0,"holonomicAngularVelocity":0.0},{"time":0.9059678991572908,"pose":{"rotation":{"radians":0.0},"translation":{"x":6.220528502711575,"y":0.7999999999999988}},"velocity":2.361686036662934,"acceleration":-2.9999999999999796,"curvature":0,"holonomicRotation":0.0,"angularVelocity":0.0,"holonomicAngularVelocity":0.0},{"time":0.9114377830914762,"pose":{"rotation":{"radians":0.0},"translation":{"x":6.2334017717757275,"y":0.7999999999999988}},"velocity":2.3452763848603784,"acceleration":-2.9999999999999596,"curvature":0,"holonomicRotation":0.0,"angularVelocity":0.0,"holonomicAngularVelocity":0.0},{"time":0.9169373573535746,"pose":{"rotation":{"radians":0.0},"translation":{"x":6.246254425443817,"y":0.7999999999999988}},"velocity":2.3287776620740828,"acceleration":-3.0000000000000404,"curvature":0,"holonomicRotation":0.0,"angularVelocity":0.0,"holonomicAngularVelocity":0.0},{"time":0.9224665285588985,"pose":{"rotation":{"radians":0.0},"translation":{"x":6.2590847782352315,"y":0.7999999999999988}},"velocity":2.312190148458111,"acceleration":-3.00000000000002,"curvature":0,"holonomicRotation":0.0,"angularVelocity":0.0,"holonomicAngularVelocity":0.0},{"time":0.9280252040652256,"pose":{"rotation":{"radians":0.0},"translation":{"x":6.271891144669359,"y":0.7999999999999988}},"velocity":2.2955141219391297,"acceleration":-3.0,"curvature":0,"holonomicRotation":0.0,"angularVelocity":0.0,"holonomicAngularVelocity":0.0},{"time":0.9336132919637808,"pose":{"rotation":{"radians":0.0},"translation":{"x":6.284671839265587,"y":0.7999999999999988}},"velocity":2.2787498582434638,"acceleration":-3.0000000000000395,"curvature":0,"holonomicRotation":0.0,"angularVelocity":0.0,"holonomicAngularVelocity":0.0},{"time":0.9392307010703641,"pose":{"rotation":{"radians":0.0},"translation":{"x":6.297425176543303,"y":0.7999999999999988}},"velocity":2.261897630923714,"acceleration":-3.0,"curvature":0,"holonomicRotation":0.0,"angularVelocity":0.0,"holonomicAngularVelocity":0.0},{"time":0.944877340916618,"pose":{"rotation":{"radians":0.0},"translation":{"x":6.310149471021894,"y":0.7999999999999988}},"velocity":2.244957711384952,"acceleration":-3.0000000000000195,"curvature":0,"holonomicRotation":0.0,"angularVelocity":0.0,"holonomicAngularVelocity":0.0},{"time":0.9505531217414389,"pose":{"rotation":{"radians":0.0},"translation":{"x":6.32284303722075,"y":0.7999999999999988}},"velocity":2.2279303689104895,"acceleration":-3.0,"curvature":0,"holonomicRotation":0.0,"angularVelocity":0.0,"holonomicAngularVelocity":0.0},{"time":0.9562579544825205,"pose":{"rotation":{"radians":0.0},"translation":{"x":6.335504189659255,"y":0.7999999999999988}},"velocity":2.2108158706872447,"acceleration":-3.0,"curvature":0,"holonomicRotation":0.0,"angularVelocity":0.0,"holonomicAngularVelocity":0.0},{"time":0.9619917507680381,"pose":{"rotation":{"radians":0.0},"translation":{"x":6.348131242856799,"y":0.7999999999999988}},"velocity":2.1936144818306915,"acceleration":-3.000000000000058,"curvature":0,"holonomicRotation":0.0,"angularVelocity":0.0,"holonomicAngularVelocity":0.0},{"time":0.9677544229084578,"pose":{"rotation":{"radians":0.0},"translation":{"x":6.360722511332769,"y":0.7999999999999988}},"velocity":2.1763264654094323,"acceleration":-3.000000000000019,"curvature":0,"holonomicRotation":0.0,"angularVelocity":0.0,"holonomicAngularVelocity":0.0},{"time":0.9735458838884795,"pose":{"rotation":{"radians":0.0},"translation":{"x":6.373276309606552,"y":0.7999999999999988}},"velocity":2.158952082469367,"acceleration":-3.000000000000019,"curvature":0,"holonomicRotation":0.0,"angularVelocity":0.0,"holonomicAngularVelocity":0.0},{"time":0.9793660473591057,"pose":{"rotation":{"radians":0.0},"translation":{"x":6.385790952197535,"y":0.7999999999999988}},"velocity":2.141491592057488,"acceleration":-3.0000000000000573,"curvature":0,"holonomicRotation":0.0,"angularVelocity":0.0,"holonomicAngularVelocity":0.0},{"time":0.9852148276298338,"pose":{"rotation":{"radians":0.0},"translation":{"x":6.398264753625108,"y":0.7999999999999988}},"velocity":2.1239452512453036,"acceleration":-3.0000000000000377,"curvature":0,"holonomicRotation":0.0,"angularVelocity":0.0,"holonomicAngularVelocity":0.0},{"time":0.9910921396609684,"pose":{"rotation":{"radians":0.0},"translation":{"x":6.4106960284086565,"y":0.7999999999999988}},"velocity":2.1063133151519,"acceleration":-3.0,"curvature":0,"holonomicRotation":0.0,"angularVelocity":0.0,"holonomicAngularVelocity":0.0},{"time":0.9969978990560587,"pose":{"rotation":{"radians":0.0},"translation":{"x":6.42308309106757,"y":0.7999999999999988}},"velocity":2.0885960369666288,"acceleration":-3.0000000000000187,"curvature":0,"holonomicRotation":0.0,"angularVelocity":0.0,"holonomicAngularVelocity":0.0},{"time":1.0029320220544455,"pose":{"rotation":{"radians":0.0},"translation":{"x":6.435424256121233,"y":0.7999999999999988}},"velocity":2.070793667971468,"acceleration":-3.000000000000056,"curvature":0,"holonomicRotation":0.0,"angularVelocity":0.0,"holonomicAngularVelocity":0.0},{"time":1.0088944255239312,"pose":{"rotation":{"radians":0.0},"translation":{"x":6.447717838089035,"y":0.7999999999999988}},"velocity":2.052906457563011,"acceleration":-3.0,"curvature":0,"holonomicRotation":0.0,"angularVelocity":0.0,"holonomicAngularVelocity":0.0},{"time":1.0148850269535554,"pose":{"rotation":{"radians":0.0},"translation":{"x":6.459962151490364,"y":0.7999999999999988}},"velocity":2.0349346532741386,"acceleration":-2.999999999999963,"curvature":0,"holonomicRotation":0.0,"angularVelocity":0.0,"holonomicAngularVelocity":0.0},{"time":1.0209037444464866,"pose":{"rotation":{"radians":0.0},"translation":{"x":6.472155510844607,"y":0.7999999999999988}},"velocity":2.0168785007953454,"acceleration":-2.999999999999963,"curvature":0,"holonomicRotation":0.0,"angularVelocity":0.0,"holonomicAngularVelocity":0.0},{"time":1.0269504967130185,"pose":{"rotation":{"radians":0.0},"translation":{"x":6.484296230671152,"y":0.7999999999999988}},"velocity":1.9987382439957493,"acceleration":-3.000000000000037,"curvature":0,"holonomicRotation":0.0,"angularVelocity":0.0,"holonomicAngularVelocity":0.0},{"time":1.0330252030636762,"pose":{"rotation":{"radians":0.0},"translation":{"x":6.496382625489385,"y":0.7999999999999988}},"velocity":1.9805141249437763,"acceleration":-3.0,"curvature":0,"holonomicRotation":0.0,"angularVelocity":-1.455414546631293e-12,"holonomicAngularVelocity":0.0},{"time":1.039127783402425,"pose":{"rotation":{"radians":-8.881784197001252e-15},"translation":{"x":6.508413009818695,"y":0.7999999999999987}},"velocity":1.9622063839275299,"acceleration":-2.9999999999999636,"curvature":0,"holonomicRotation":0.0,"angularVelocity":1.4488158491653932e-12,"holonomicAngularVelocity":0.0},{"time":1.0452581582199822,"pose":{"rotation":{"radians":0.0},"translation":{"x":6.520385698178469,"y":0.7999999999999987}},"velocity":1.9438152594748583,"acceleration":-3.0,"curvature":0,"holonomicRotation":0.0,"angularVelocity":0.0,"holonomicAngularVelocity":0.0},{"time":1.051416248587231,"pose":{"rotation":{"radians":0.0},"translation":{"x":6.532299005088095,"y":0.7999999999999987}},"velocity":1.925340988373112,"acceleration":-3.000000000000036,"curvature":0,"holonomicRotation":0.0,"angularVelocity":0.0,"holonomicAngularVelocity":0.0},{"time":1.0576019761487299,"pose":{"rotation":{"radians":0.0},"translation":{"x":6.544151245066961,"y":0.7999999999999987}},"velocity":1.9067838056886155,"acceleration":-2.999999999999964,"curvature":0,"holonomicRotation":0.0,"angularVelocity":0.0,"holonomicAngularVelocity":0.0},{"time":1.0638152631163242,"pose":{"rotation":{"radians":0.0},"translation":{"x":6.555940732634453,"y":0.7999999999999987}},"velocity":1.8881439447858326,"acceleration":-2.9999999999999645,"curvature":0,"holonomicRotation":0.0,"angularVelocity":0.0,"holonomicAngularVelocity":0.0},{"time":1.0700560322628494,"pose":{"rotation":{"radians":0.0},"translation":{"x":6.567665782309961,"y":0.7999999999999987}},"velocity":1.869421637346257,"acceleration":-3.0,"curvature":0,"holonomicRotation":0.0,"angularVelocity":0.0,"holonomicAngularVelocity":0.0},{"time":1.0763242069159282,"pose":{"rotation":{"radians":0.0},"translation":{"x":6.579324708612869,"y":0.7999999999999987}},"velocity":1.8506171133870204,"acceleration":-3.0000000000000355,"curvature":0,"holonomicRotation":0.0,"angularVelocity":0.0,"holonomicAngularVelocity":0.0},{"time":1.0826197109518634,"pose":{"rotation":{"radians":0.0},"translation":{"x":6.590915826062568,"y":0.7999999999999987}},"velocity":1.8317306012792147,"acceleration":-3.000000000000035,"curvature":0,"holonomicRotation":0.0,"angularVelocity":0.0,"holonomicAngularVelocity":0.0},{"time":1.088942468789615,"pose":{"rotation":{"radians":0.0},"translation":{"x":6.602437449178444,"y":0.7999999999999987}},"velocity":1.8127623277659597,"acceleration":-3.000000000000035,"curvature":0,"holonomicRotation":0.0,"angularVelocity":0.0,"holonomicAngularVelocity":0.0},{"time":1.0952924053848732,"pose":{"rotation":{"radians":0.0},"translation":{"x":6.613887892479885,"y":0.7999999999999987}},"velocity":1.793712517980185,"acceleration":-3.000000000000035,"curvature":0,"holonomicRotation":0.0,"angularVelocity":1.5320526969863208e-12,"holonomicAngularVelocity":0.0},{"time":1.1016694462242123,"pose":{"rotation":{"radians":9.769962616701378e-15},"translation":{"x":6.625265470486278,"y":0.7999999999999988}},"velocity":1.7745813954621679,"acceleration":-2.9999999999999654,"curvature":0,"holonomicRotation":0.0,"angularVelocity":-1.5255862203254438e-12,"holonomicAngularVelocity":0.0},{"time":1.1080735173193335,"pose":{"rotation":{"radians":0.0},"translation":{"x":6.63656849771701,"y":0.7999999999999988}},"velocity":1.755369182176804,"acceleration":-3.0000000000000346,"curvature":0,"holonomicRotation":0.0,"angularVelocity":0.0,"holonomicAngularVelocity":0.0},{"time":1.1145045452013955,"pose":{"rotation":{"radians":0.0},"translation":{"x":6.647795288691472,"y":0.7999999999999988}},"velocity":1.736076098530618,"acceleration":-2.9999999999999654,"curvature":0,"holonomicRotation":0.0,"angularVelocity":0.0,"holonomicAngularVelocity":0.0},{"time":1.120962456915417,"pose":{"rotation":{"radians":0.0},"translation":{"x":6.658944157929047,"y":0.7999999999999988}},"velocity":1.7167023633885532,"acceleration":-3.000000000000034,"curvature":0,"holonomicRotation":0.0,"angularVelocity":0.0,"holonomicAngularVelocity":0.0},{"time":1.1274471800147765,"pose":{"rotation":{"radians":0.0},"translation":{"x":6.670013419949124,"y":0.7999999999999988}},"velocity":1.697248194090475,"acceleration":-3.0,"curvature":0,"holonomicRotation":0.0,"angularVelocity":-1.5004252201685043e-12,"holonomicAngularVelocity":0.0},{"time":1.1339586425557782,"pose":{"rotation":{"radians":-9.769962616701378e-15},"translation":{"x":6.681001389271093,"y":0.7999999999999987}},"velocity":1.67771380646747,"acceleration":-3.0,"curvature":0,"holonomicRotation":0.0,"angularVelocity":1.4943052241189991e-12,"holonomicAngularVelocity":0.0},{"time":1.1404967730923032,"pose":{"rotation":{"radians":0.0},"translation":{"x":6.691906380414339,"y":0.7999999999999987}},"velocity":1.6580994148578947,"acceleration":-3.0,"curvature":0,"holonomicRotation":0.0,"angularVelocity":0.0,"holonomicAngularVelocity":0.0},{"time":1.1470615006705405,"pose":{"rotation":{"radians":0.0},"translation":{"x":6.70272670789825,"y":0.7999999999999987}},"velocity":1.6384052321231832,"acceleration":-2.9999999999999662,"curvature":0,"holonomicRotation":0.0,"angularVelocity":0.0,"holonomicAngularVelocity":0.0},{"time":1.1536527548237872,"pose":{"rotation":{"radians":0.0},"translation":{"x":6.713460686242215,"y":0.7999999999999987}},"velocity":1.618631469663443,"acceleration":-3.0000000000000338,"curvature":0,"holonomicRotation":0.0,"angularVelocity":1.5434418671915614e-12,"holonomicAngularVelocity":0.0},{"time":1.1602704655673326,"pose":{"rotation":{"radians":1.021405182655144e-14},"translation":{"x":6.724106629965619,"y":0.7999999999999988}},"velocity":1.5987783374328068,"acceleration":-2.9999999999999662,"curvature":0,"holonomicRotation":0.0,"angularVelocity":-1.537312076661852e-12,"holonomicAngularVelocity":0.0},{"time":1.16691456339341,"pose":{"rotation":{"radians":0.0},"translation":{"x":6.734662853587852,"y":0.7999999999999988}},"velocity":1.578846043954575,"acceleration":-2.9999999999999667,"curvature":0,"holonomicRotation":0.0,"angularVelocity":0.0,"holonomicAngularVelocity":0.0},{"time":1.1735849792662232,"pose":{"rotation":{"radians":0.0},"translation":{"x":6.745127671628301,"y":0.7999999999999988}},"velocity":1.5588347963361355,"acceleration":-2.9999999999999667,"curvature":0,"holonomicRotation":0.0,"angularVelocity":0.0,"holonomicAngularVelocity":0.0},{"time":1.1802816446170463,"pose":{"rotation":{"radians":0.0},"translation":{"x":6.755499398606351,"y":0.7999999999999988}},"velocity":1.538744800283666,"acceleration":-3.0000000000000333,"curvature":0,"holonomicRotation":0.0,"angularVelocity":0.0,"holonomicAngularVelocity":0.0},{"time":1.187004491339397,"pose":{"rotation":{"radians":0.0},"translation":{"x":6.765776349041394,"y":0.7999999999999988}},"velocity":1.5185762601166137,"acceleration":-3.000000000000066,"curvature":0,"holonomicRotation":0.0,"angularVelocity":0.0,"holonomicAngularVelocity":0.0},{"time":1.19375345178427,"pose":{"rotation":{"radians":0.0},"translation":{"x":6.7759568374528145,"y":0.7999999999999988}},"velocity":1.4983293787819942,"acceleration":-3.0,"curvature":0,"holonomicRotation":0.0,"angularVelocity":0.0,"holonomicAngularVelocity":0.0},{"time":1.2005284587554528,"pose":{"rotation":{"radians":0.0},"translation":{"x":6.786039178360001,"y":0.7999999999999988}},"velocity":1.4780043578684459,"acceleration":-3.000000000000033,"curvature":0,"holonomicRotation":0.0,"angularVelocity":0.0,"holonomicAngularVelocity":0.0},{"time":1.2073294455049002,"pose":{"rotation":{"radians":0.0},"translation":{"x":6.796021686282341,"y":0.7999999999999988}},"velocity":1.4576013976201034,"acceleration":-3.000000000000033,"curvature":0,"holonomicRotation":0.0,"angularVelocity":0.0,"holonomicAngularVelocity":0.0},{"time":1.2141563457281814,"pose":{"rotation":{"radians":0.0},"translation":{"x":6.805902675739221,"y":0.7999999999999988}},"velocity":1.4371206969502595,"acceleration":-3.0000000000000324,"curvature":0,"holonomicRotation":0.0,"angularVelocity":0.0,"holonomicAngularVelocity":0.0},{"time":1.2210090935599944,"pose":{"rotation":{"radians":0.0},"translation":{"x":6.815680461250031,"y":0.7999999999999988}},"velocity":1.4165624534548205,"acceleration":-3.0,"curvature":0,"holonomicRotation":0.0,"angularVelocity":1.6786027595638397e-12,"holonomicAngularVelocity":0.0},{"time":1.22788762356974,"pose":{"rotation":{"radians":1.1546319456101628e-14},"translation":{"x":6.825353357334156,"y":0.7999999999999989}},"velocity":1.395926863425584,"acceleration":-2.9999999999999676,"curvature":0,"holonomicRotation":0.0,"angularVelocity":-1.6723502421986264e-12,"holonomicAngularVelocity":0.0},{"time":1.2347918707571723,"pose":{"rotation":{"radians":0.0},"translation":{"x":6.834919678510985,"y":0.7999999999999989}},"velocity":1.375214121863287,"acceleration":-3.0,"curvature":0,"holonomicRotation":0.0,"angularVelocity":0.0,"holonomicAngularVelocity":0.0},{"time":1.241721770548106,"pose":{"rotation":{"radians":0.0},"translation":{"x":6.844377739299906,"y":0.7999999999999989}},"velocity":1.3544244224904856,"acceleration":-3.000000000000032,"curvature":0,"holonomicRotation":0.0,"angularVelocity":0.0,"holonomicAngularVelocity":0.0},{"time":1.2486772587901933,"pose":{"rotation":{"radians":0.0},"translation":{"x":6.853725854220306,"y":0.7999999999999989}},"velocity":1.333557957764224,"acceleration":-2.999999999999968,"curvature":0,"holonomicRotation":0.0,"angularVelocity":0.0,"holonomicAngularVelocity":0.0},{"time":1.2556582717487639,"pose":{"rotation":{"radians":0.0},"translation":{"x":6.862962337791571,"y":0.7999999999999989}},"velocity":1.3126149188885126,"acceleration":-2.999999999999968,"curvature":0,"holonomicRotation":0.0,"angularVelocity":0.0,"holonomicAngularVelocity":0.0},{"time":1.2626647461027327,"pose":{"rotation":{"radians":0.0},"translation":{"x":6.872085504533091,"y":0.7999999999999989}},"velocity":1.2915954958266063,"acceleration":-2.9999999999999685,"curvature":0,"holonomicRotation":0.0,"angularVelocity":-1.7683052811902524e-12,"holonomicAngularVelocity":0.0},{"time":1.2696966189405676,"pose":{"rotation":{"radians":-1.2434497875801753e-14},"translation":{"x":6.881093668964253,"y":0.7999999999999988}},"velocity":1.2704998773131018,"acceleration":-2.9999999999999685,"curvature":0,"holonomicRotation":0.0,"angularVelocity":1.761956915322761e-12,"holonomicAngularVelocity":0.0},{"time":1.2767538277563257,"pose":{"rotation":{"radians":0.0},"translation":{"x":6.8899851456044425,"y":0.7999999999999988}},"velocity":1.2493282508658277,"acceleration":-2.9999999999999685,"curvature":0,"holonomicRotation":0.0,"angularVelocity":0.0,"holonomicAngularVelocity":0.0},{"time":1.283836310445758,"pose":{"rotation":{"radians":0.0},"translation":{"x":6.898758248973049,"y":0.7999999999999988}},"velocity":1.228080802797531,"acceleration":-3.0,"curvature":0,"holonomicRotation":0.0,"angularVelocity":1.8119217756629342e-12,"holonomicAngularVelocity":0.0},{"time":1.2909440053024743,"pose":{"rotation":{"radians":1.2878587085651816e-14},"translation":{"x":6.907411293589461,"y":0.7999999999999989}},"velocity":1.206757718227382,"acceleration":-2.999999999999969,"curvature":0,"holonomicRotation":0.0,"angularVelocity":-1.8055328274547153e-12,"holonomicAngularVelocity":0.0},{"time":1.2980768510141787,"pose":{"rotation":{"radians":0.0},"translation":{"x":6.915942593973065,"y":0.7999999999999989}},"velocity":1.185359181092269,"acceleration":-3.0,"curvature":0,"holonomicRotation":0.0,"angularVelocity":0.0,"holonomicAngularVelocity":0.0},{"time":1.305234786658973,"pose":{"rotation":{"radians":0.0},"translation":{"x":6.924350464643247,"y":0.7999999999999989}},"velocity":1.1638853741578854,"acceleration":-3.000000000000062,"curvature":0,"holonomicRotation":0.0,"angularVelocity":0.0,"holonomicAngularVelocity":0.0},{"time":1.3124177517017348,"pose":{"rotation":{"radians":0.0},"translation":{"x":6.9326332201193965,"y":0.7999999999999989}},"velocity":1.1423364790296,"acceleration":-3.000000000000031,"curvature":0,"holonomicRotation":0.0,"angularVelocity":0.0,"holonomicAngularVelocity":0.0},{"time":1.3196256859905588,"pose":{"rotation":{"radians":0.0},"translation":{"x":6.9407891749209005,"y":0.7999999999999989}},"velocity":1.1207126761631279,"acceleration":-3.0,"curvature":0,"holonomicRotation":0.0,"angularVelocity":0.0,"holonomicAngularVelocity":0.0},{"time":1.3268585297532804,"pose":{"rotation":{"radians":0.0},"translation":{"x":6.948816643567146,"y":0.7999999999999989}},"velocity":1.099014144874963,"acceleration":-3.0,"curvature":0,"holonomicRotation":0.0,"angularVelocity":0.0,"holonomicAngularVelocity":0.0},{"time":1.334116223594076,"pose":{"rotation":{"radians":0.0},"translation":{"x":6.956713940577522,"y":0.7999999999999989}},"velocity":1.0772410633525764,"acceleration":-3.0,"curvature":0,"holonomicRotation":0.0,"angularVelocity":0.0,"holonomicAngularVelocity":0.0},{"time":1.3413987084901409,"pose":{"rotation":{"radians":0.0},"translation":{"x":6.964479380471416,"y":0.7999999999999989}},"velocity":1.055393608664382,"acceleration":-2.9999999999999694,"curvature":0,"holonomicRotation":0.0,"angularVelocity":0.0,"holonomicAngularVelocity":0.0},{"time":1.3487059257884564,"pose":{"rotation":{"radians":0.0},"translation":{"x":6.972111277768213,"y":0.7999999999999989}},"velocity":1.0334719567694355,"acceleration":-3.0,"curvature":0,"holonomicRotation":0.0,"angularVelocity":0.0,"holonomicAngularVelocity":0.0},{"time":1.356037817202657,"pose":{"rotation":{"radians":0.0},"translation":{"x":6.979607946987303,"y":0.7999999999999989}},"velocity":1.0114762825268335,"acceleration":-3.0,"curvature":0,"holonomicRotation":0.0,"angularVelocity":2.0524729859413055e-12,"holonomicAngularVelocity":0.0},{"time":1.36339432480998,"pose":{"rotation":{"radians":1.509903313490213e-14},"translation":{"x":6.986967702648074,"y":0.799999999999999}},"velocity":0.9894067597048646,"acceleration":-3.0,"curvature":0,"holonomicRotation":0.0,"angularVelocity":-2.045643901207213e-12,"holonomicAngularVelocity":0.0},{"time":1.3707753910483373,"pose":{"rotation":{"radians":0.0},"translation":{"x":6.9941888592699115,"y":0.799999999999999}},"velocity":0.9672635609897924,"acceleration":-3.00000000000003,"curvature":0,"holonomicRotation":0.0,"angularVelocity":0.0,"holonomicAngularVelocity":0.0},{"time":1.3781809587135017,"pose":{"rotation":{"radians":0.0},"translation":{"x":7.001269731372204,"y":0.799999999999999}},"velocity":0.9450468579942991,"acceleration":-3.000000000000045,"curvature":0,"holonomicRotation":0.0,"angularVelocity":0.0,"holonomicAngularVelocity":0.0},{"time":1.3856109709564208,"pose":{"rotation":{"radians":0.0},"translation":{"x":7.008208633474339,"y":0.799999999999999}},"velocity":0.9227568212655415,"acceleration":-3.000000000000015,"curvature":0,"holonomicRotation":0.0,"angularVelocity":0.0,"holonomicAngularVelocity":0.0},{"time":1.393065371280683,"pose":{"rotation":{"radians":0.0},"translation":{"x":7.015003880095705,"y":0.799999999999999}},"velocity":0.900393620292755,"acceleration":-2.999999999999955,"curvature":0,"holonomicRotation":0.0,"angularVelocity":0.0,"holonomicAngularVelocity":0.0},{"time":1.4005441035401447,"pose":{"rotation":{"radians":0.0},"translation":{"x":7.021653785755689,"y":0.799999999999999}},"velocity":0.8779574235143702,"acceleration":-3.0,"curvature":0,"holonomicRotation":0.0,"angularVelocity":0.0,"holonomicAngularVelocity":0.0},{"time":1.408047111936747,"pose":{"rotation":{"radians":0.0},"translation":{"x":7.028156664973677,"y":0.799999999999999}},"velocity":0.8554483983245633,"acceleration":-2.9999999999999853,"curvature":0,"holonomicRotation":0.0,"angularVelocity":0.0,"holonomicAngularVelocity":0.0},{"time":1.4155743410185577,"pose":{"rotation":{"radians":0.0},"translation":{"x":7.034510832269059,"y":0.799999999999999}},"velocity":0.8328667110791311,"acceleration":-3.0000000000000147,"curvature":0,"holonomicRotation":0.0,"angularVelocity":0.0,"holonomicAngularVelocity":0.0},{"time":1.4231257356780551,"pose":{"rotation":{"radians":0.0},"translation":{"x":7.04071460216122,"y":0.799999999999999}},"velocity":0.810212527100639,"acceleration":-3.0,"curvature":0,"holonomicRotation":0.0,"angularVelocity":2.4034907861299162e-12,"holonomicAngularVelocity":0.0},{"time":1.4307012411507307,"pose":{"rotation":{"radians":1.8207657603852567e-14},"translation":{"x":7.046766289169551,"y":0.7999999999999992}},"velocity":0.7874860106826124,"acceleration":-2.9999999999999707,"curvature":0,"holonomicRotation":0.0,"angularVelocity":-2.3958825431516174e-12,"holonomicAngularVelocity":0.0},{"time":1.4383008030140187,"pose":{"rotation":{"radians":0.0},"translation":{"x":7.052664207813437,"y":0.7999999999999992}},"velocity":0.7646873250927485,"acceleration":-2.9999999999999707,"curvature":0,"holonomicRotation":0.0,"angularVelocity":0.0,"holonomicAngularVelocity":0.0},{"time":1.445924367186687,"pose":{"rotation":{"radians":0.0},"translation":{"x":7.058406672612265,"y":0.7999999999999992}},"velocity":0.7418166325747436,"acceleration":-3.0,"curvature":0,"holonomicRotation":0.0,"angularVelocity":2.5550693267891383e-12,"holonomicAngularVelocity":0.0},{"time":1.453571879928722,"pose":{"rotation":{"radians":1.9539925233402755e-14},"translation":{"x":7.063991998085425,"y":0.7999999999999993}},"velocity":0.7188740943486385,"acceleration":-3.0000000000000147,"curvature":0,"holonomicRotation":0.0,"angularVelocity":-2.5471107070123603e-12,"holonomicAngularVelocity":0.0},{"time":1.461243287841856,"pose":{"rotation":{"radians":0.0},"translation":{"x":7.069418498752303,"y":0.7999999999999993}},"velocity":0.6958598706092369,"acceleration":-2.999999999999971,"curvature":0,"holonomicRotation":0.0,"angularVelocity":0.0,"holonomicAngularVelocity":0.0},{"time":1.468938537870873,"pose":{"rotation":{"radians":0.0},"translation":{"x":7.074684489132287,"y":0.7999999999999993}},"velocity":0.6727741205221859,"acceleration":-2.999999999999986,"curvature":0,"holonomicRotation":0.0,"angularVelocity":0.0,"holonomicAngularVelocity":0.0},{"time":1.4766575773059003,"pose":{"rotation":{"radians":0.0},"translation":{"x":7.079788283744764,"y":0.7999999999999993}},"velocity":0.6496170022171043,"acceleration":-2.999999999999971,"curvature":0,"holonomicRotation":0.0,"angularVelocity":0.0,"holonomicAngularVelocity":0.0},{"time":1.4844003537859207,"pose":{"rotation":{"radians":0.0},"translation":{"x":7.084728197109123,"y":0.7999999999999993}},"velocity":0.6263886727770431,"acceleration":-2.999999999999986,"curvature":0,"holonomicRotation":0.0,"angularVelocity":0.0,"holonomicAngularVelocity":0.0},{"time":1.4921668153038528,"pose":{"rotation":{"radians":0.0},"translation":{"x":7.08950254374475,"y":0.7999999999999993}},"velocity":0.603089288223247,"acceleration":-3.0,"curvature":0,"holonomicRotation":0.0,"angularVelocity":0.0,"holonomicAngularVelocity":0.0},{"time":1.499956910213645,"pose":{"rotation":{"radians":0.0},"translation":{"x":7.094109638171033,"y":0.7999999999999993}},"velocity":0.5797190034938702,"acceleration":-3.0000000000000284,"curvature":0,"holonomicRotation":0.0,"angularVelocity":3.182751944795663e-12,"holonomicAngularVelocity":0.0},{"time":1.5077705872399896,"pose":{"rotation":{"radians":2.4868995751603507e-14},"translation":{"x":7.09854779490736,"y":0.7999999999999994}},"velocity":0.5562779724148363,"acceleration":-3.0,"curvature":0,"holonomicRotation":0.0,"angularVelocity":-3.173195729094066e-12,"holonomicAngularVelocity":0.0},{"time":1.5156077954914653,"pose":{"rotation":{"radians":0.0},"translation":{"x":7.102815328473119,"y":0.7999999999999994}},"velocity":0.5327663476604091,"acceleration":-3.000000000000014,"curvature":0,"holonomicRotation":0.0,"angularVelocity":0.0,"holonomicAngularVelocity":0.0},{"time":1.5234684844782773,"pose":{"rotation":{"radians":0.0},"translation":{"x":7.106910553387696,"y":0.7999999999999994}},"velocity":0.5091842806999731,"acceleration":-2.999999999999986,"curvature":0,"holonomicRotation":0.0,"angularVelocity":0.0,"holonomicAngularVelocity":0.0},{"time":1.531352604136161,"pose":{"rotation":{"radians":0.0},"translation":{"x":7.110831784170478,"y":0.7999999999999994}},"velocity":0.4855319217263221,"acceleration":-3.000000000000028,"curvature":0,"holonomicRotation":0.0,"angularVelocity":3.7065931295254684e-12,"holonomicAngularVelocity":0.0},{"time":1.5392601048587602,"pose":{"rotation":{"radians":2.930988785010413e-14},"translation":{"x":7.114577335340857,"y":0.7999999999999995}},"velocity":0.4618094195585245,"acceleration":-2.999999999999972,"curvature":0,"holonomicRotation":0.0,"angularVelocity":-3.695688589314052e-12,"holonomicAngularVelocity":0.0},{"time":1.5471909375417012,"pose":{"rotation":{"radians":0.0},"translation":{"x":7.1181455214182145,"y":0.7999999999999995}},"velocity":0.43801692150970156,"acceleration":-2.999999999999979,"curvature":0,"holonomicRotation":0.0,"angularVelocity":0.0,"holonomicAngularVelocity":0.0},{"time":1.5551450536433291,"pose":{"rotation":{"radians":0.0},"translation":{"x":7.121534656921943,"y":0.7999999999999995}},"velocity":0.4141545732048178,"acceleration":-3.0000000000000138,"curvature":0,"holonomicRotation":0.0,"angularVelocity":4.34216266158279e-12,"holonomicAngularVelocity":0.0},{"time":1.5631224052692303,"pose":{"rotation":{"radians":3.4638958368304884e-14},"translation":{"x":7.124743056371428,"y":0.7999999999999996}},"velocity":0.3902225183271146,"acceleration":-2.9999999999999583,"curvature":0,"holonomicRotation":0.0,"angularVelocity":-4.32957753730359e-12,"holonomicAngularVelocity":0.0},{"time":1.5711229452918667,"pose":{"rotation":{"radians":0.0},"translation":{"x":7.127769034286057,"y":0.7999999999999996}},"velocity":0.36622089825920545,"acceleration":-2.999999999999993,"curvature":0,"holonomicRotation":0.0,"angularVelocity":0.0,"holonomicAngularVelocity":0.0},{"time":1.5791466275228483,"pose":{"rotation":{"radians":0.0},"translation":{"x":7.130610905185218,"y":0.7999999999999996}},"velocity":0.3421498515662604,"acceleration":-3.0000000000000346,"curvature":0,"holonomicRotation":0.0,"angularVelocity":5.1877134223327515e-12,"holonomicAngularVelocity":0.0},{"time":1.587193406966408,"pose":{"rotation":{"radians":4.1744385725905886e-14},"translation":{"x":7.133266983588299,"y":0.7999999999999997}},"velocity":0.3180095132355811,"acceleration":-3.0000000000000275,"curvature":0,"holonomicRotation":0.0,"angularVelocity":-5.172893231945167e-12,"holonomicAngularVelocity":0.0},{"time":1.5952632402017266,"pose":{"rotation":{"radians":0.0},"translation":{"x":7.135735584014686,"y":0.7999999999999997}},"velocity":0.2938000135296254,"acceleration":-2.9999999999999725,"curvature":0,"holonomicRotation":0.0,"angularVelocity":0.0,"holonomicAngularVelocity":0.0},{"time":1.603356085976729,"pose":{"rotation":{"radians":0.0},"translation":{"x":7.138015020983768,"y":0.7999999999999997}},"velocity":0.26952147620461786,"acceleration":-3.0000000000000204,"curvature":0,"holonomicRotation":0.0,"angularVelocity":0.0,"holonomicAngularVelocity":0.0},{"time":1.611471906162566,"pose":{"rotation":{"radians":0.0},"translation":{"x":7.140103609014933,"y":0.7999999999999997}},"velocity":0.2451740156471072,"acceleration":-2.9999999999999964,"curvature":0,"holonomicRotation":0.0,"angularVelocity":0.0,"holonomicAngularVelocity":0.0},{"time":1.6196106673518884,"pose":{"rotation":{"radians":0.0},"translation":{"x":7.141999662627566,"y":0.7999999999999997}},"velocity":0.22075773207913973,"acceleration":-3.000000000000017,"curvature":0,"holonomicRotation":0.0,"angularVelocity":0.0,"holonomicAngularVelocity":0.0},{"time":1.6277723436701124,"pose":{"rotation":{"radians":0.0},"translation":{"x":7.143701496341056,"y":0.7999999999999997}},"velocity":0.1962727031244676,"acceleration":-3.000000000000034,"curvature":0,"holonomicRotation":0.0,"angularVelocity":0.0,"holonomicAngularVelocity":0.0},{"time":1.6359569220270862,"pose":{"rotation":{"radians":0.0},"translation":{"x":7.145207424674791,"y":0.7999999999999997}},"velocity":0.1717189680535464,"acceleration":-2.9999999999999627,"curvature":0,"holonomicRotation":0.0,"angularVelocity":0.0,"holonomicAngularVelocity":0.0},{"time":1.644164412696093,"pose":{"rotation":{"radians":0.0},"translation":{"x":7.14651576214816,"y":0.7999999999999997}},"velocity":0.1470964960465256,"acceleration":-3.0000000000000338,"curvature":0,"holonomicRotation":0.0,"angularVelocity":0.0,"holonomicAngularVelocity":0.0},{"time":1.652394872804387,"pose":{"rotation":{"radians":0.0},"translation":{"x":7.147624823280549,"y":0.7999999999999997}},"velocity":0.12240511572164428,"acceleration":-2.9999999999999662,"curvature":0,"holonomicRotation":0.0,"angularVelocity":2.959305907473214e-11,"holonomicAngularVelocity":0.0},{"time":1.6606484658107985,"pose":{"rotation":{"radians":2.4424906541753444e-13},"translation":{"x":7.148532922591345,"y":0.7999999999999999}},"velocity":0.09764433670240937,"acceleration":-3.000000000000015,"curvature":0,"holonomicRotation":0.0,"angularVelocity":-1.0515841265229472e-11,"holonomicAngularVelocity":0.0},{"time":1.6689256433504038,"pose":{"rotation":{"radians":1.5720758028692217e-13},"translation":{"x":7.149238374599935,"y":0.8}},"velocity":0.07281280408359331,"acceleration":-3.0000000000000084,"curvature":0,"holonomicRotation":0.0,"angularVelocity":-1.8935531784548654e-11,"holonomicAngularVelocity":0.0},{"time":1.6772278965997793,"pose":{"rotation":{"radians":0.0},"translation":{"x":7.149739493825709,"y":0.8}},"velocity":0.047906044335466816,"acceleration":-2.9999999999999982,"curvature":0,"holonomicRotation":0.0,"angularVelocity":0.0,"holonomicAngularVelocity":0.0},{"time":1.6855634389658258,"pose":{"rotation":{"radians":0.0},"translation":{"x":7.150034594788052,"y":0.8}},"velocity":0.022899417237327142,"acceleration":-3.000000000000021,"curvature":0,"holonomicRotation":0.0,"angularVelocity":0.0,"holonomicAngularVelocity":0.0},{"time":1.693196578044935,"pose":{"rotation":{"radians":0.0},"translation":{"x":7.150121992006354,"y":0.8}},"velocity":0,"acceleration":-2.999999999999972,"curvature":0,"holonomicRotation":0.0,"angularVelocity":0.0,"holonomicAngularVelocity":0.0}]